myNowTime/__init__.py
myNowTime/myNowTime.py
myNowTime-0.0.1.dist-info/METADATA
myNowTime-0.0.1.dist-info/WHEEL
myNowTime-0.0.1.dist-info/top_level.txt
myNowTime-0.0.1.dist-info/RECORD
