Metadata-Version: 2.1
Name: myNowTime
Version: 0.0.1
Summary: Module for time processing
Author: Toshihiro Nishimura
Author-email: tnishimura@se.kanazawa-u.ac.jp
License: MIT
